[{"title": "1 - K\u00fcnstliche Intelligenz I 2017/2018", "itunes_title": null, "episode": null, "date": "Thu, 19 Oct 2017 00:00:00 +0200", "link": null, "author": "Prof. Dr. Michael Kohlhase", "description": null, "summary": ""}, {"title": "1 - K\u00fcnstliche Intelligenz I 2017/2018", "itunes_title": null, "episode": null, "date": "Thu, 19 Oct 2017 00:00:00 +0200", "link": null, "author": "Prof. Dr. Michael Kohlhase", "description": null, "summary": ""}, {"title": "2 - K\u00fcnstliche Intelligenz I 2017/2018", "itunes_title": null, "episode": null, "date": "Wed, 25 Oct 2017 00:00:00 +0200", "link": null, "author": "Prof. Dr. Michael Kohlhase", "description": null, "summary": ""}, {"title": "2 - K\u00fcnstliche Intelligenz I 2017/2018", "itunes_title": null, "episode": null, "date": "Wed, 25 Oct 2017 00:00:00 +0200", "link": null, "author": "Prof. Dr. Michael Kohlhase", "description": null, "summary": ""}, {"title": "3 - K\u00fcnstliche Intelligenz I 2017/2018", "itunes_title": null, "episode": null, "date": "Thu, 26 Oct 2017 00:00:00 +0200", "link": null, "author": "Prof. Dr. Michael Kohlhase", "description": null, "summary": ""}, {"title": "3 - K\u00fcnstliche Intelligenz I 2017/2018", "itunes_title": null, "episode": null, "date": "Thu, 26 Oct 2017 00:00:00 +0200", "link": null, "author": "Prof. Dr. Michael Kohlhase", "description": null, "summary": ""}, {"title": "4 - K\u00fcnstliche Intelligenz I 2017/2018", "itunes_title": null, "episode": null, "date": "Thu, 02 Nov 2017 00:00:00 +0100", "link": null, "author": "Prof. Dr. Michael Kohlhase", "description": null, "summary": ""}, {"title": "4 - K\u00fcnstliche Intelligenz I 2017/2018", "itunes_title": null, "episode": null, "date": "Thu, 02 Nov 2017 00:00:00 +0100", "link": null, "author": "Prof. Dr. Michael Kohlhase", "description": null, "summary": ""}, {"title": "5 - K\u00fcnstliche Intelligenz I 2017/2018", "itunes_title": null, "episode": null, "date": "Wed, 08 Nov 2017 00:00:00 +0100", "link": null, "author": "Prof. Dr. Michael Kohlhase", "description": null, "summary": ""}, {"title": "5 - K\u00fcnstliche Intelligenz I 2017/2018", "itunes_title": null, "episode": null, "date": "Wed, 08 Nov 2017 00:00:00 +0100", "link": null, "author": "Prof. Dr. Michael Kohlhase", "description": null, "summary": ""}, {"title": "6 - K\u00fcnstliche Intelligenz I 2017/2018", "itunes_title": null, "episode": null, "date": "Thu, 09 Nov 2017 00:00:00 +0100", "link": null, "author": "Prof. Dr. Michael Kohlhase", "description": null, "summary": ""}, {"title": "6 - K\u00fcnstliche Intelligenz I 2017/2018", "itunes_title": null, "episode": null, "date": "Thu, 09 Nov 2017 00:00:00 +0100", "link": null, "author": "Prof. Dr. Michael Kohlhase", "description": null, "summary": ""}, {"title": "7 - K\u00fcnstliche Intelligenz I 2017/2018", "itunes_title": null, "episode": null, "date": "Wed, 15 Nov 2017 00:00:00 +0100", "link": null, "author": "Prof. Dr. Michael Kohlhase", "description": null, "summary": ""}, {"title": "7 - K\u00fcnstliche Intelligenz I 2017/2018", "itunes_title": null, "episode": null, "date": "Wed, 15 Nov 2017 00:00:00 +0100", "link": null, "author": "Prof. Dr. Michael Kohlhase", "description": null, "summary": ""}, {"title": "8 - K\u00fcnstliche Intelligenz I 2017/2018", "itunes_title": null, "episode": null, "date": "Thu, 16 Nov 2017 00:00:00 +0100", "link": null, "author": "Dennis M\u00fcller", "description": null, "summary": ""}, {"title": "8 - K\u00fcnstliche Intelligenz I 2017/2018", "itunes_title": null, "episode": null, "date": "Thu, 16 Nov 2017 00:00:00 +0100", "link": null, "author": "Dennis M\u00fcller", "description": null, "summary": ""}, {"title": "9 - K\u00fcnstliche Intelligenz I 2017/2018", "itunes_title": null, "episode": null, "date": "Wed, 22 Nov 2017 00:00:00 +0100", "link": null, "author": "Dennis M\u00fcller", "description": null, "summary": ""}, {"title": "9 - K\u00fcnstliche Intelligenz I 2017/2018", "itunes_title": null, "episode": null, "date": "Wed, 22 Nov 2017 00:00:00 +0100", "link": null, "author": "Dennis M\u00fcller", "description": null, "summary": ""}, {"title": "10 - K\u00fcnstliche Intelligenz I 2017/2018", "itunes_title": null, "episode": null, "date": "Thu, 23 Nov 2017 00:00:00 +0100", "link": null, "author": "Prof. Dr. Michael Kohlhase", "description": null, "summary": ""}, {"title": "10 - K\u00fcnstliche Intelligenz I 2017/2018", "itunes_title": null, "episode": null, "date": "Thu, 23 Nov 2017 00:00:00 +0100", "link": null, "author": "Prof. Dr. Michael Kohlhase", "description": null, "summary": ""}, {"title": "11 - K\u00fcnstliche Intelligenz I 2017/2018", "itunes_title": null, "episode": null, "date": "Wed, 29 Nov 2017 00:00:00 +0100", "link": null, "author": "Prof. Dr. Michael Kohlhase", "description": null, "summary": ""}, {"title": "11 - K\u00fcnstliche Intelligenz I 2017/2018", "itunes_title": null, "episode": null, "date": "Wed, 29 Nov 2017 00:00:00 +0100", "link": null, "author": "Prof. Dr. Michael Kohlhase", "description": null, "summary": ""}, {"title": "12 - K\u00fcnstliche Intelligenz I 2017/2018", "itunes_title": null, "episode": null, "date": "Thu, 30 Nov 2017 00:00:00 +0100", "link": null, "author": "Prof. Dr. Michael Kohlhase", "description": null, "summary": ""}, {"title": "12 - K\u00fcnstliche Intelligenz I 2017/2018", "itunes_title": null, "episode": null, "date": "Thu, 30 Nov 2017 00:00:00 +0100", "link": null, "author": "Prof. Dr. Michael Kohlhase", "description": null, "summary": ""}, {"title": "13 - K\u00fcnstliche Intelligenz I 2017/2018", "itunes_title": null, "episode": null, "date": "Wed, 06 Dec 2017 00:00:00 +0100", "link": null, "author": "Prof. Dr. Michael Kohlhase", "description": null, "summary": ""}, {"title": "13 - K\u00fcnstliche Intelligenz I 2017/2018", "itunes_title": null, "episode": null, "date": "Wed, 06 Dec 2017 00:00:00 +0100", "link": null, "author": "Prof. Dr. Michael Kohlhase", "description": null, "summary": ""}, {"title": "14 - K\u00fcnstliche Intelligenz I 2017/2018", "itunes_title": null, "episode": null, "date": "Thu, 07 Dec 2017 00:00:00 +0100", "link": null, "author": "Prof. Dr. Michael Kohlhase", "description": null, "summary": ""}, {"title": "14 - K\u00fcnstliche Intelligenz I 2017/2018", "itunes_title": null, "episode": null, "date": "Thu, 07 Dec 2017 00:00:00 +0100", "link": null, "author": "Prof. Dr. Michael Kohlhase", "description": null, "summary": ""}, {"title": "15 - K\u00fcnstliche Intelligenz I 2017/2018", "itunes_title": null, "episode": null, "date": "Thu, 14 Dec 2017 00:00:00 +0100", "link": null, "author": "Prof. Dr. Michael Kohlhase", "description": null, "summary": ""}, {"title": "15 - K\u00fcnstliche Intelligenz I 2017/2018", "itunes_title": null, "episode": null, "date": "Thu, 14 Dec 2017 00:00:00 +0100", "link": null, "author": "Prof. Dr. Michael Kohlhase", "description": null, "summary": ""}, {"title": "16 - K\u00fcnstliche Intelligenz I 2017/2018", "itunes_title": null, "episode": null, "date": "Wed, 20 Dec 2017 00:00:00 +0100", "link": null, "author": "Prof. Dr. Michael Kohlhase", "description": null, "summary": ""}, {"title": "16 - K\u00fcnstliche Intelligenz I 2017/2018", "itunes_title": null, "episode": null, "date": "Wed, 20 Dec 2017 00:00:00 +0100", "link": null, "author": "Prof. Dr. Michael Kohlhase", "description": null, "summary": ""}, {"title": "17 - K\u00fcnstliche Intelligenz I 2017/2018", "itunes_title": null, "episode": null, "date": "Thu, 21 Dec 2017 00:00:00 +0100", "link": null, "author": "Prof. Dr. Michael Kohlhase", "description": null, "summary": ""}, {"title": "17 - K\u00fcnstliche Intelligenz I 2017/2018", "itunes_title": null, "episode": null, "date": "Thu, 21 Dec 2017 00:00:00 +0100", "link": null, "author": "Prof. Dr. Michael Kohlhase", "description": null, "summary": ""}, {"title": "18 - K\u00fcnstliche Intelligenz I 2017/2018", "itunes_title": null, "episode": null, "date": "Wed, 10 Jan 2018 00:00:00 +0100", "link": null, "author": "Prof. Dr. Michael Kohlhase", "description": null, "summary": ""}, {"title": "18 - K\u00fcnstliche Intelligenz I 2017/2018", "itunes_title": null, "episode": null, "date": "Wed, 10 Jan 2018 00:00:00 +0100", "link": null, "author": "Prof. Dr. Michael Kohlhase", "description": null, "summary": ""}, {"title": "19 - K\u00fcnstliche Intelligenz I 2017/2018", "itunes_title": null, "episode": null, "date": "Thu, 11 Jan 2018 00:00:00 +0100", "link": null, "author": "Prof. Dr. Michael Kohlhase", "description": null, "summary": ""}, {"title": "19 - K\u00fcnstliche Intelligenz I 2017/2018", "itunes_title": null, "episode": null, "date": "Thu, 11 Jan 2018 00:00:00 +0100", "link": null, "author": "Prof. Dr. Michael Kohlhase", "description": null, "summary": ""}, {"title": "20 - K\u00fcnstliche Intelligenz I 2017/2018", "itunes_title": null, "episode": null, "date": "Wed, 17 Jan 2018 00:00:00 +0100", "link": null, "author": "Prof. Dr. Michael Kohlhase", "description": null, "summary": ""}, {"title": "21 - K\u00fcnstliche Intelligenz I 2017/2018", "itunes_title": null, "episode": null, "date": "Thu, 18 Jan 2018 00:00:00 +0100", "link": null, "author": "Prof. Dr. Michael Kohlhase", "description": null, "summary": ""}, {"title": "21 - K\u00fcnstliche Intelligenz I 2017/2018", "itunes_title": null, "episode": null, "date": "Thu, 18 Jan 2018 00:00:00 +0100", "link": null, "author": "Prof. Dr. Michael Kohlhase", "description": null, "summary": ""}, {"title": "22 - K\u00fcnstliche Intelligenz I 2017/2018", "itunes_title": null, "episode": null, "date": "Wed, 24 Jan 2018 00:00:00 +0100", "link": null, "author": "Prof. Dr. Michael Kohlhase", "description": null, "summary": ""}, {"title": "22 - K\u00fcnstliche Intelligenz I 2017/2018", "itunes_title": null, "episode": null, "date": "Wed, 24 Jan 2018 00:00:00 +0100", "link": null, "author": "Prof. Dr. Michael Kohlhase", "description": null, "summary": ""}, {"title": "23 - K\u00fcnstliche Intelligenz I 2017/2018", "itunes_title": null, "episode": null, "date": "Thu, 25 Jan 2018 00:00:00 +0100", "link": null, "author": "Prof. Dr. Michael Kohlhase", "description": null, "summary": ""}, {"title": "23 - K\u00fcnstliche Intelligenz I 2017/2018", "itunes_title": null, "episode": null, "date": "Thu, 25 Jan 2018 00:00:00 +0100", "link": null, "author": "Prof. Dr. Michael Kohlhase", "description": null, "summary": ""}, {"title": "24 - K\u00fcnstliche Intelligenz I 2017/2018", "itunes_title": null, "episode": null, "date": "Wed, 31 Jan 2018 00:00:00 +0100", "link": null, "author": "Prof. Dr. Michael Kohlhase", "description": null, "summary": ""}, {"title": "25 - K\u00fcnstliche Intelligenz I 2017/2018", "itunes_title": null, "episode": null, "date": "Thu, 01 Feb 2018 00:00:00 +0100", "link": null, "author": "Prof. Dr. Michael Kohlhase", "description": null, "summary": ""}, {"title": "25 - K\u00fcnstliche Intelligenz I 2017/2018", "itunes_title": null, "episode": null, "date": "Thu, 01 Feb 2018 00:00:00 +0100", "link": null, "author": "Prof. Dr. Michael Kohlhase", "description": null, "summary": ""}, {"title": "26 - K\u00fcnstliche Intelligenz I 2017/2018", "itunes_title": null, "episode": null, "date": "Wed, 07 Feb 2018 00:00:00 +0100", "link": null, "author": "Prof. Dr. Michael Kohlhase", "description": null, "summary": ""}, {"title": "26 - K\u00fcnstliche Intelligenz I 2017/2018", "itunes_title": null, "episode": null, "date": "Wed, 07 Feb 2018 00:00:00 +0100", "link": null, "author": "Prof. Dr. Michael Kohlhase", "description": null, "summary": ""}, {"title": "27 - K\u00fcnstliche Intelligenz I 2017/2018", "itunes_title": null, "episode": null, "date": "Thu, 08 Feb 2018 00:00:00 +0100", "link": null, "author": "Prof. Dr. Michael Kohlhase", "description": null, "summary": ""}, {"title": "27 - K\u00fcnstliche Intelligenz I 2017/2018", "itunes_title": null, "episode": null, "date": "Thu, 08 Feb 2018 00:00:00 +0100", "link": null, "author": "Prof. Dr. Michael Kohlhase", "description": null, "summary": ""}, {"title": "1 - K\u00fcnstliche Intelligenz I 2017/2018", "itunes_title": null, "episode": null, "date": "Thu, 19 Oct 2017 00:00:00 +0200", "link": null, "author": "Prof. Dr. Michael Kohlhase", "description": null, "summary": ""}, {"title": "2 - K\u00fcnstliche Intelligenz I 2017/2018", "itunes_title": null, "episode": null, "date": "Wed, 25 Oct 2017 00:00:00 +0200", "link": null, "author": "Prof. Dr. Michael Kohlhase", "description": null, "summary": ""}, {"title": "3 - K\u00fcnstliche Intelligenz I 2017/2018", "itunes_title": null, "episode": null, "date": "Thu, 26 Oct 2017 00:00:00 +0200", "link": null, "author": "Prof. Dr. Michael Kohlhase", "description": null, "summary": ""}, {"title": "4 - K\u00fcnstliche Intelligenz I 2017/2018", "itunes_title": null, "episode": null, "date": "Thu, 02 Nov 2017 00:00:00 +0100", "link": null, "author": "Prof. Dr. Michael Kohlhase", "description": null, "summary": ""}, {"title": "5 - K\u00fcnstliche Intelligenz I 2017/2018", "itunes_title": null, "episode": null, "date": "Wed, 08 Nov 2017 00:00:00 +0100", "link": null, "author": "Prof. Dr. Michael Kohlhase", "description": null, "summary": ""}, {"title": "6 - K\u00fcnstliche Intelligenz I 2017/2018", "itunes_title": null, "episode": null, "date": "Thu, 09 Nov 2017 00:00:00 +0100", "link": null, "author": "Prof. Dr. Michael Kohlhase", "description": null, "summary": ""}, {"title": "7 - K\u00fcnstliche Intelligenz I 2017/2018", "itunes_title": null, "episode": null, "date": "Wed, 15 Nov 2017 00:00:00 +0100", "link": null, "author": "Prof. Dr. Michael Kohlhase", "description": null, "summary": ""}, {"title": "8 - K\u00fcnstliche Intelligenz I 2017/2018", "itunes_title": null, "episode": null, "date": "Thu, 16 Nov 2017 00:00:00 +0100", "link": null, "author": "Dennis M\u00fcller", "description": null, "summary": ""}, {"title": "9 - K\u00fcnstliche Intelligenz I 2017/2018", "itunes_title": null, "episode": null, "date": "Wed, 22 Nov 2017 00:00:00 +0100", "link": null, "author": "Dennis M\u00fcller", "description": null, "summary": ""}, {"title": "10 - K\u00fcnstliche Intelligenz I 2017/2018", "itunes_title": null, "episode": null, "date": "Thu, 23 Nov 2017 00:00:00 +0100", "link": null, "author": "Prof. Dr. Michael Kohlhase", "description": null, "summary": ""}, {"title": "11 - K\u00fcnstliche Intelligenz I 2017/2018", "itunes_title": null, "episode": null, "date": "Wed, 29 Nov 2017 00:00:00 +0100", "link": null, "author": "Prof. Dr. Michael Kohlhase", "description": null, "summary": ""}, {"title": "12 - K\u00fcnstliche Intelligenz I 2017/2018", "itunes_title": null, "episode": null, "date": "Thu, 30 Nov 2017 00:00:00 +0100", "link": null, "author": "Prof. Dr. Michael Kohlhase", "description": null, "summary": ""}, {"title": "13 - K\u00fcnstliche Intelligenz I 2017/2018", "itunes_title": null, "episode": null, "date": "Wed, 06 Dec 2017 00:00:00 +0100", "link": null, "author": "Prof. Dr. Michael Kohlhase", "description": null, "summary": ""}, {"title": "14 - K\u00fcnstliche Intelligenz I 2017/2018", "itunes_title": null, "episode": null, "date": "Thu, 07 Dec 2017 00:00:00 +0100", "link": null, "author": "Prof. Dr. Michael Kohlhase", "description": null, "summary": ""}, {"title": "15 - K\u00fcnstliche Intelligenz I 2017/2018", "itunes_title": null, "episode": null, "date": "Thu, 14 Dec 2017 00:00:00 +0100", "link": null, "author": "Prof. Dr. Michael Kohlhase", "description": null, "summary": ""}, {"title": "16 - K\u00fcnstliche Intelligenz I 2017/2018", "itunes_title": null, "episode": null, "date": "Wed, 20 Dec 2017 00:00:00 +0100", "link": null, "author": "Prof. Dr. Michael Kohlhase", "description": null, "summary": ""}, {"title": "17 - K\u00fcnstliche Intelligenz I 2017/2018", "itunes_title": null, "episode": null, "date": "Thu, 21 Dec 2017 00:00:00 +0100", "link": null, "author": "Prof. Dr. Michael Kohlhase", "description": null, "summary": ""}, {"title": "18 - K\u00fcnstliche Intelligenz I 2017/2018", "itunes_title": null, "episode": null, "date": "Wed, 10 Jan 2018 00:00:00 +0100", "link": null, "author": "Prof. Dr. Michael Kohlhase", "description": null, "summary": ""}, {"title": "19 - K\u00fcnstliche Intelligenz I 2017/2018", "itunes_title": null, "episode": null, "date": "Thu, 11 Jan 2018 00:00:00 +0100", "link": null, "author": "Prof. Dr. Michael Kohlhase", "description": null, "summary": ""}, {"title": "21 - K\u00fcnstliche Intelligenz I 2017/2018", "itunes_title": null, "episode": null, "date": "Thu, 18 Jan 2018 00:00:00 +0100", "link": null, "author": "Prof. Dr. Michael Kohlhase", "description": null, "summary": ""}, {"title": "23 - K\u00fcnstliche Intelligenz I 2017/2018", "itunes_title": null, "episode": null, "date": "Thu, 25 Jan 2018 00:00:00 +0100", "link": null, "author": "Prof. Dr. Michael Kohlhase", "description": null, "summary": ""}, {"title": "25 - K\u00fcnstliche Intelligenz I 2017/2018", "itunes_title": null, "episode": null, "date": "Thu, 01 Feb 2018 00:00:00 +0100", "link": null, "author": "Prof. Dr. Michael Kohlhase", "description": null, "summary": ""}, {"title": "26 - K\u00fcnstliche Intelligenz I 2017/2018", "itunes_title": null, "episode": null, "date": "Wed, 07 Feb 2018 00:00:00 +0100", "link": null, "author": "Prof. Dr. Michael Kohlhase", "description": null, "summary": ""}, {"title": "27 - K\u00fcnstliche Intelligenz I 2017/2018", "itunes_title": null, "episode": null, "date": "Thu, 08 Feb 2018 00:00:00 +0100", "link": null, "author": "Prof. Dr. Michael Kohlhase", "description": null, "summary": ""}, {"title": "KIT im Rathaus - Mittwoch, 27. Januar 2017: Das KIT-Zentrum Information \u00b7 Systeme \u00b7 Technologien stellt sich vor", "itunes_title": null, "episode": null, "date": "Tue, 14 Feb 2017 09:45:00 +0100", "link": null, "author": "Prof. Dr. Tamim Asfour", "description": null, "summary": "Der wissenschaftliche Sprecher des KIT Zentrums Information-Systeme-Technologien, Prof. Dr. Tamim Asfour, stellt die Arbeit des Zentrums vor.\n\nWeitere Informationen zum KIT in Rathaus unter:\nhttp://www.zak.kit.edu/kit_im_rathaus.php"}, {"title": "KIT im Rathaus - Mittwoch, 27. Januar 2017: Humanoide Roboter auf dem Vormarsch", "itunes_title": null, "episode": null, "date": "Tue, 14 Feb 2017 09:39:49 +0100", "link": null, "author": "Prof. Dr. Tamim Asfour", "description": null, "summary": "In seinem Vortrag spricht Prof. Dr. Tamim Asfour, der wissenschaftliche Sprecher des KIT-Zentrums Information \u00b7 Systeme \u00b7 Technologien, \u00fcber Nutzung von Robotern in Wirschaft, Forschung und Alltag.\n\nDer Vortrag fand statt im Rahmen der Reihe &quot;KIT im Rathaus&quot; am 25.1.2017\n\nWeitere Informationen zum KIT in Rathaus unter:\nhttp://www.zak.kit.edu/kit_im_rathaus..."}, {"title": "Interview mit Ingmar Wolff:", "itunes_title": "Interview mit Ingmar Wolff:", "episode": "12", "date": "Sun, 07 Jul 2019 10:53:13 +0000", "link": "https://www.tobias-budig.com/2019/07/07/ki-in-der-landwirtschaft-anwendung-von-kuenstlicher-intelligenz/", "author": "Tobias Budig", "description": "Was ist KI? Wie kontrolliert man KI's? Wie kann man KI in der Landwirtschaft nutzen? Und viele weitere Fragen beantwortet Ingmar, der aktuell am Karlsruher Institut f\u00fcr Technologie (KIT) daran forscht, wie KI's andere KI's verbessern k\u00f6nnen. Zudem hat er Heliopas AI gegr\u00fcndet, wo sie Landwirten unterst\u00fctzen Sch\u00e4dlingsbefall fr\u00fchzeitig zu entdecken. Au\u00dferdem arbeiten sie daran, mithilfe von Satellitendaten ein Risikomodell zu entwickeln, damit zuk\u00fcnftig Versicherungen gegen D\u00fcrre angeboten werden k\u00f6nnen.", "summary": "Was ist KI? Wie kontrolliert man KI's? Wie kann man KI in der Landwirtschaft nutzen? Und viele weitere Fragen beantwortet Ingmar, der aktuell am Karlsruher Institut f\u00fcr Technologie (KIT) daran forscht, wie KI's andere KI's verbessern k\u00f6nnen. Zudem hat er Heliopas AI gegr\u00fcndet, wo sie Landwirten unterst\u00fctzen Sch\u00e4dlingsbefall fr\u00fchzeitig zu entdecken. Au\u00dferdem arbeiten sie daran, mithilfe von Satellitendaten ein Risikomodell zu entwickeln, damit zuk\u00fcnftig Versicherungen gegen D\u00fcrre angeboten werden k\u00f6nnen."}, {"title": "KI f\u00fcr Dummies #2 - Was ist Machine Learning? Was kann es, was nicht?", "itunes_title": "KI f\u00fcr Dummies #2 - Was ist Machine Learning? Was kann es, was nicht?", "episode": "11", "date": "Thu, 18 Apr 2019 07:45:40 +0000", "link": "https://www.tobias-budig.com/2019/04/18/ki-fuer-dummies-2/", "author": "Tobias Budig", "description": "In dieser Episode lernst Du, was machine learning und deep learning ist. Anwendungsf\u00e4lle und Faustregeln, wann ich machine learning anwenden kann. Au\u00dferdem skizziere ich die Funktion eines Neuronalen Netztes f\u00fcr nicht-Techies. Wie werde ich ein KI-Unternehmen?\n\nF\u00fcr weitere Fragen und Ideen schreibe mir gerne unter podcast@tobias-budig.com\n\nTeile die Folge mit deinen Freunden, damit sie auch erfahren, was KI ist!", "summary": "In dieser Episode lernst Du, was machine learning und deep learning ist. Anwendungsf\u00e4lle und Faustregeln, wann ich machine learning anwenden kann. Au\u00dferdem skizziere ich die Funktion eines Neuronalen Netztes f\u00fcr nicht-Techies. Wie werde ich ein KI-Unternehmen?\n\nF\u00fcr weitere Fragen und Ideen schreibe mir gerne unter podcast@tobias-budig.com\n\nTeile die Folge mit deinen Freunden, damit sie auch erfahren, was KI ist!"}, {"title": "KI f\u00fcr Dummies #1 - \u00dcbersicht", "itunes_title": "KI f\u00fcr Dummies #1 - \u00dcbersicht", "episode": "10", "date": "Wed, 17 Apr 2019 12:27:38 +0000", "link": "https://www.tobias-budig.com/2019/04/17/ki-fuer-dummies-1/", "author": "Tobias Budig", "description": "In dieser Episode starte ich meine Reihe zur verst\u00e4ndlichen Erk\u00e4rung von K\u00fcnstlicher Intelligenz, machine learning und data science.", "summary": null}, {"title": "KI2go News KW7", "itunes_title": "KI2go News KW7", "episode": "9", "date": "Wed, 20 Feb 2019 11:28:29 +0000", "link": "https://www.tobias-budig.com/2019/02/20/ki2go-news-kw7/", "author": "Tobias Budig", "description": "+++ Goolge fordert Regeln f\u00fcr KI?\nhttps://www.wired.com/story/google-says-wants-rules-ai-kinda-sorta/\n+++\nAlphaStar gewinnt gegen Mensch in Starcraft \nhttps://www.heise.de/newsticker/meldung/Starcraft-2-DeepMind-KI-schlaegt-Profi-Spieler-4288223.html\nhttps://www.theverge.com/2019/1/24/18196135/google-deepmind-ai-starcraft-2-victory\n+++\n Steht uns ein KI Winter bevor?\nhttps://t3n.de/news/deep-learning-ende-1140464/\nHype Cycle: https://de.wikipedia.org/wiki/Hype-Zyklus\n+++\nSong: NOW\u00cb - Horizon (Vlog No Copyright Music) \nMusic provided by Vlog No Copyright Music. \nVideo Link: https://youtu.be/g845F6ORCOc", "summary": "+++ Goolge fordert Regeln f\u00fcr KI?\nhttps://www.wired.com/story/google-says-wants-rules-ai-kinda-sorta/\n+++\nAlphaStar gewinnt gegen Mensch in Starcraft \nhttps://www.heise.de/newsticker/meldung/Starcraft-2-DeepMind-KI-schlaegt-Profi-Spieler-4288223.html\nhttps://www.theverge.com/2019/1/24/18196135/google-deepmind-ai-starcraft-2-victory\n+++\n Steht uns ein KI Winter bevor?\nhttps://t3n.de/news/deep-learning-ende-1140464/\nHype Cycle: https://de.wikipedia.org/wiki/Hype-Zyklus\n+++\nSong: NOW\u00cb - Horizon (Vlog No Copyright Music) \nMusic provided by Vlog No Copyright Music. \nVideo Link: https://youtu.be/g845F6ORCOc"}, {"title": "Die letzten Wochen + Interview mit  Elisabeth von TortenGl\u00fcck", "itunes_title": "Die letzten Wochen + Interview mit  Elisabeth von TortenGl\u00fcck", "episode": "8", "date": "Sat, 02 Feb 2019 15:17:38 +0000", "link": "https://www.tobias-budig.com/2019/02/02/interview-mit-elisabeth-von-tortenglueck/", "author": "Tobias Budig", "description": "Was ist TortenGl\u00fcck? Das erf\u00e4hrst du in dem Interview mit Elisabeth von TortenGl\u00fcck.", "summary": "Was ist TortenGl\u00fcck? Das erf\u00e4hrst du in dem Interview mit Elisabeth von TortenGl\u00fcck."}, {"title": "Was ist so toll an Hackathons?", "itunes_title": "Was ist so toll an Hackathons?", "episode": "7", "date": "Sun, 04 Nov 2018 19:24:04 +0000", "link": "https://www.tobias-budig.com/2018/11/04/hackathon/", "author": "Tobias Budig", "description": "Du suchst nach offenen, pro-aktiven Programmierern?  Du bist selbst Coder und suchst nach gleichgesinnten? Oder bist Du Unternehmer und suchst nach Mitarbeitern f\u00fcr Dein Team? - Dann ist ein Hackathon genau das richtige f\u00fcr Dich! \nIch habe bei den Hackathons, an denen ich teilgenommen habe, bisher wirklich inspirierende Leute kennen gelernt. Daher finde ich dass sie auf jeden Fall loheneswert sind. Auch das Essen ist meistens gut ;)", "summary": "Du suchst nach offenen, pro-aktiven Programmierern?  Du bist selbst Coder und suchst nach gleichgesinnten? Oder bist Du Unternehmer und suchst nach Mitarbeitern f\u00fcr Dein Team? - Dann ist ein Hackathon genau das richtige f\u00fcr Dich! \nIch habe bei den Hackathons, an denen ich teilgenommen habe, bisher wirklich inspirierende Leute kennen gelernt. Daher finde ich dass sie auf jeden Fall loheneswert sind. Auch das Essen ist meistens gut ;)"}, {"title": "Was ist ein Neuronales Netz und wie funktioniert es?", "itunes_title": "Was ist ein Neuronales Netz und wie funktioniert es?", "episode": "6", "date": "Fri, 19 Oct 2018 17:36:42 +0000", "link": "https://www.tobias-budig.com/2018/10/19/neuronales-netz/", "author": "Tobias Budig", "description": "Neuronale Netzte oder Deep Learning sind der Grund f\u00fcr den atemberaubenden Erfolg von Maschine Learning. Egal ob es es um \u00dcbersetzungen oder autonomes Fahren geht. Komplexe Prozesse lassen sich mit ihnen Abbilden.", "summary": "Neuronale Netzte oder Deep Learning sind der Grund f\u00fcr den atemberaubenden Erfolg von Maschine Learning. Egal ob es es um \u00dcbersetzungen oder autonomes Fahren geht. Komplexe Prozesse lassen sich mit ihnen Abbilden."}, {"title": "Wie funktioniert maschinelles Lernen", "itunes_title": "Wie funktioniert maschinelles Lernen", "episode": "5", "date": "Wed, 26 Sep 2018 14:25:14 +0000", "link": "https://www.tobias-budig.com/2018/09/26/wie-funktioniert-maschinelles-lernen/", "author": "Tobias Budig", "description": "Wie lernen Maschinen? Wo liegt die Schwierigkeit dabei? \nK\u00fcnstliche Intelligenz, insbesonder maschinelles Lernen ist keine Hexerei. \nIn der Ersten Folge der kleinen Reihe \u00fcber maschinelles Lernen geht es um das \"Supervised Learning\". Hierbei ist in dem Datensatz das Ergebnis bekannt. Aus dem Zusammenhang Inputdaten und Ergebnis wird versucht ein m\u00f6glichts gutes mathematisches Modell zu finden. Nun k\u00f6nnen zu neuen unbekannten Inpudaten die Ergebnisse vorhergesagt werden.", "summary": "Wie lernen Maschinen? Wo liegt die Schwierigkeit dabei? \nK\u00fcnstliche Intelligenz, insbesonder maschinelles Lernen ist keine Hexerei. \nIn der Ersten Folge der kleinen Reihe \u00fcber maschinelles Lernen geht es um das \"Supervised Learning\". Hierbei ist in dem Datensatz das Ergebnis bekannt. Aus dem Zusammenhang Inputdaten und Ergebnis wird versucht ein m\u00f6glichts gutes mathematisches Modell zu finden. Nun k\u00f6nnen zu neuen unbekannten Inpudaten die Ergebnisse vorhergesagt werden."}, {"title": "5G -  Das Netz der Zukunft", "itunes_title": "5G -  Das Netz der Zukunft", "episode": "4", "date": "Tue, 04 Sep 2018 20:00:05 +0000", "link": "https://www.tobias-budig.com/2018/09/04/5g-das-netz-der-zukunft/", "author": "Tobias Budig", "description": "Daten in einem Wimpernschlag versenden? Austausch fast in Echtzeit? Das soll der neue Mobilfunkstandard 5G k\u00f6nnen. Er ist der Nachfolger von LTE und k\u00f6nnte insbesondere in der klassischen Industrie als Katalystor f\u00fcr weitere Entwicklungen dienen.\nIn G\u00e4llivare, ein Dorf im Norden von Schweden, gibt es eines der ersten 5G netzte der Welt. Hier entsteht eine vernetzte Mine, in der Menschenleben geschutzt werden. Doch das ist nur eines der Beispiele aus der Folge.", "summary": "Daten in einem Wimpernschlag versenden? Austausch fast in Echtzeit? Das soll der neue Mobilfunkstandard 5G k\u00f6nnen. Er ist der Nachfolger von LTE und k\u00f6nnte insbesondere in der klassischen Industrie als Katalystor f\u00fcr weitere Entwicklungen dienen.\nIn G\u00e4llivare, ein Dorf im Norden von Schweden, gibt es eines der ersten 5G netzte der Welt. Hier entsteht eine vernetzte Mine, in der Menschenleben geschutzt werden. Doch das ist nur eines der Beispiele aus der Folge."}, {"title": "003 Autonomes Fahren - Wie funktioniert das eigentlich?", "itunes_title": "003 Autonomes Fahren - Wie funktioniert das eigentlich?", "episode": "3", "date": "Wed, 08 Aug 2018 23:48:58 +0000", "link": "https://www.tobias-budig.com/2018/08/09/autonomes-fahren/", "author": "Tobias Budig", "description": "Damit Autos autonom fahren k\u00f6nnen m\u00fcssen viele Systeme ineinandergreifen und eine gro\u00dfe Menge an Daten verarbeitet werden.", "summary": "Damit Autos autonom fahren k\u00f6nnen m\u00fcssen viele Systeme ineinandergreifen und eine gro\u00dfe Menge an Daten verarbeitet werden."}, {"title": "1 - K\u00fcnstliche Intelligenz II 2017", "itunes_title": null, "episode": null, "date": "Thu, 04 May 2017 00:00:00 +0200", "link": null, "author": "Prof. Dr. Michael Kohlhase", "description": null, "summary": "Dieser Kurs besch\u00e4ftigt sich mit den Grundlagen der K\u00fcnstlichen Intelligenz (KI), insbesondere mit Techniken des Schliessens unter Unsicherheit, des maschinellen Lernens und dem Sprachverstehen."}, {"title": "2 - K\u00fcnstliche Intelligenz II 2017", "itunes_title": null, "episode": null, "date": "Mon, 08 May 2017 00:00:00 +0200", "link": null, "author": "Prof. Dr. Michael Kohlhase", "description": null, "summary": "Dieser Kurs besch\u00e4ftigt sich mit den Grundlagen der K\u00fcnstlichen Intelligenz (KI), insbesondere mit Techniken des Schliessens unter Unsicherheit, des maschinellen Lernens und dem Sprachverstehen."}, {"title": "3 - K\u00fcnstliche Intelligenz II 2017", "itunes_title": null, "episode": null, "date": "Thu, 11 May 2017 00:00:00 +0200", "link": null, "author": "Prof. Dr. Michael Kohlhase", "description": null, "summary": "Dieser Kurs besch\u00e4ftigt sich mit den Grundlagen der K\u00fcnstlichen Intelligenz (KI), insbesondere mit Techniken des Schliessens unter Unsicherheit, des maschinellen Lernens und dem Sprachverstehen."}, {"title": "4 - K\u00fcnstliche Intelligenz II 2017", "itunes_title": null, "episode": null, "date": "Mon, 15 May 2017 00:00:00 +0200", "link": null, "author": "Prof. Dr. Michael Kohlhase", "description": null, "summary": "Dieser Kurs besch\u00e4ftigt sich mit den Grundlagen der K\u00fcnstlichen Intelligenz (KI), insbesondere mit Techniken des Schliessens unter Unsicherheit, des maschinellen Lernens und dem Sprachverstehen."}, {"title": "5 - K\u00fcnstliche Intelligenz II 2017", "itunes_title": null, "episode": null, "date": "Thu, 18 May 2017 00:00:00 +0200", "link": null, "author": "Prof. Dr. Michael Kohlhase", "description": null, "summary": "Dieser Kurs besch\u00e4ftigt sich mit den Grundlagen der K\u00fcnstlichen Intelligenz (KI), insbesondere mit Techniken des Schliessens unter Unsicherheit, des maschinellen Lernens und dem Sprachverstehen."}, {"title": "6 - K\u00fcnstliche Intelligenz II 2017", "itunes_title": null, "episode": null, "date": "Mon, 22 May 2017 00:00:00 +0200", "link": null, "author": "Prof. Dr. Michael Kohlhase", "description": null, "summary": "Dieser Kurs besch\u00e4ftigt sich mit den Grundlagen der K\u00fcnstlichen Intelligenz (KI), insbesondere mit Techniken des Schliessens unter Unsicherheit, des maschinellen Lernens und dem Sprachverstehen."}, {"title": "7 - K\u00fcnstliche Intelligenz II 2017", "itunes_title": null, "episode": null, "date": "Mon, 29 May 2017 00:00:00 +0200", "link": null, "author": "Prof. Dr. Michael Kohlhase", "description": null, "summary": "Dieser Kurs besch\u00e4ftigt sich mit den Grundlagen der K\u00fcnstlichen Intelligenz (KI), insbesondere mit Techniken des Schliessens unter Unsicherheit, des maschinellen Lernens und dem Sprachverstehen."}, {"title": "8 - K\u00fcnstliche Intelligenz II 2017", "itunes_title": null, "episode": null, "date": "Thu, 01 Jun 2017 00:00:00 +0200", "link": null, "author": "Prof. Dr. Michael Kohlhase", "description": null, "summary": "Dieser Kurs besch\u00e4ftigt sich mit den Grundlagen der K\u00fcnstlichen Intelligenz (KI), insbesondere mit Techniken des Schliessens unter Unsicherheit, des maschinellen Lernens und dem Sprachverstehen."}, {"title": "9 - K\u00fcnstliche Intelligenz II 2017", "itunes_title": null, "episode": null, "date": "Thu, 08 Jun 2017 00:00:00 +0200", "link": null, "author": "Prof. Dr. Michael Kohlhase", "description": null, "summary": "Dieser Kurs besch\u00e4ftigt sich mit den Grundlagen der K\u00fcnstlichen Intelligenz (KI), insbesondere mit Techniken des Schliessens unter Unsicherheit, des maschinellen Lernens und dem Sprachverstehen."}, {"title": "10 - K\u00fcnstliche Intelligenz II 2017", "itunes_title": null, "episode": null, "date": "Mon, 12 Jun 2017 00:00:00 +0200", "link": null, "author": "Prof. Dr. Michael Kohlhase", "description": null, "summary": "Dieser Kurs besch\u00e4ftigt sich mit den Grundlagen der K\u00fcnstlichen Intelligenz (KI), insbesondere mit Techniken des Schliessens unter Unsicherheit, des maschinellen Lernens und dem Sprachverstehen."}, {"title": "11 - K\u00fcnstliche Intelligenz II 2017", "itunes_title": null, "episode": null, "date": "Mon, 19 Jun 2017 00:00:00 +0200", "link": null, "author": "Prof. Dr. Michael Kohlhase", "description": null, "summary": "Dieser Kurs besch\u00e4ftigt sich mit den Grundlagen der K\u00fcnstlichen Intelligenz (KI), insbesondere mit Techniken des Schliessens unter Unsicherheit, des maschinellen Lernens und dem Sprachverstehen."}, {"title": "12 - K\u00fcnstliche Intelligenz II 2017", "itunes_title": null, "episode": null, "date": "Thu, 22 Jun 2017 00:00:00 +0200", "link": null, "author": "Prof. Dr. Michael Kohlhase", "description": null, "summary": "Dieser Kurs besch\u00e4ftigt sich mit den Grundlagen der K\u00fcnstlichen Intelligenz (KI), insbesondere mit Techniken des Schliessens unter Unsicherheit, des maschinellen Lernens und dem Sprachverstehen."}, {"title": "13 - K\u00fcnstliche Intelligenz II 2017", "itunes_title": null, "episode": null, "date": "Mon, 26 Jun 2017 00:00:00 +0200", "link": null, "author": "Prof. Dr. Michael Kohlhase", "description": null, "summary": "Dieser Kurs besch\u00e4ftigt sich mit den Grundlagen der K\u00fcnstlichen Intelligenz (KI), insbesondere mit Techniken des Schliessens unter Unsicherheit, des maschinellen Lernens und dem Sprachverstehen."}, {"title": "14 - K\u00fcnstliche Intelligenz II 2017", "itunes_title": null, "episode": null, "date": "Thu, 29 Jun 2017 00:00:00 +0200", "link": null, "author": "Prof. Dr. Michael Kohlhase", "description": null, "summary": "Dieser Kurs besch\u00e4ftigt sich mit den Grundlagen der K\u00fcnstlichen Intelligenz (KI), insbesondere mit Techniken des Schliessens unter Unsicherheit, des maschinellen Lernens und dem Sprachverstehen."}, {"title": "15 - K\u00fcnstliche Intelligenz II 2017", "itunes_title": null, "episode": null, "date": "Mon, 03 Jul 2017 00:00:00 +0200", "link": null, "author": "Prof. Dr. Michael Kohlhase", "description": null, "summary": "Dieser Kurs besch\u00e4ftigt sich mit den Grundlagen der K\u00fcnstlichen Intelligenz (KI), insbesondere mit Techniken des Schliessens unter Unsicherheit, des maschinellen Lernens und dem Sprachverstehen."}, {"title": "16 - K\u00fcnstliche Intelligenz II 2017", "itunes_title": null, "episode": null, "date": "Thu, 06 Jul 2017 00:00:00 +0200", "link": null, "author": "Prof. Dr. Michael Kohlhase", "description": null, "summary": "Dieser Kurs besch\u00e4ftigt sich mit den Grundlagen der K\u00fcnstlichen Intelligenz (KI), insbesondere mit Techniken des Schliessens unter Unsicherheit, des maschinellen Lernens und dem Sprachverstehen."}, {"title": "17 - K\u00fcnstliche Intelligenz II 2017", "itunes_title": null, "episode": null, "date": "Mon, 10 Jul 2017 00:00:00 +0200", "link": null, "author": "Dennis M\u00fcller", "description": null, "summary": "Dieser Kurs besch\u00e4ftigt sich mit den Grundlagen der K\u00fcnstlichen Intelligenz (KI), insbesondere mit Techniken des Schliessens unter Unsicherheit, des maschinellen Lernens und dem Sprachverstehen."}, {"title": "18 - K\u00fcnstliche Intelligenz II 2017", "itunes_title": null, "episode": null, "date": "Thu, 13 Jul 2017 00:00:00 +0200", "link": null, "author": "Dennis M\u00fcller", "description": null, "summary": "Dieser Kurs besch\u00e4ftigt sich mit den Grundlagen der K\u00fcnstlichen Intelligenz (KI), insbesondere mit Techniken des Schliessens unter Unsicherheit, des maschinellen Lernens und dem Sprachverstehen."}, {"title": "19 - K\u00fcnstliche Intelligenz II 2017", "itunes_title": null, "episode": null, "date": "Mon, 17 Jul 2017 00:00:00 +0200", "link": null, "author": "Marcel Rupprecht", "description": null, "summary": "Dieser Kurs besch\u00e4ftigt sich mit den Grundlagen der K\u00fcnstlichen Intelligenz (KI), insbesondere mit Techniken des Schliessens unter Unsicherheit, des maschinellen Lernens und dem Sprachverstehen."}, {"title": "20 - K\u00fcnstliche Intelligenz II 2017", "itunes_title": null, "episode": null, "date": "Mon, 24 Jul 2017 00:00:00 +0200", "link": null, "author": "Prof. Dr. Michael Kohlhase", "description": null, "summary": "Dieser Kurs besch\u00e4ftigt sich mit den Grundlagen der K\u00fcnstlichen Intelligenz (KI), insbesondere mit Techniken des Schliessens unter Unsicherheit, des maschinellen Lernens und dem Sprachverstehen."}, {"title": "21 - K\u00fcnstliche Intelligenz II 2017", "itunes_title": null, "episode": null, "date": "Thu, 27 Jul 2017 00:00:00 +0200", "link": null, "author": "Prof. Dr. Michael Kohlhase", "description": null, "summary": "Dieser Kurs besch\u00e4ftigt sich mit den Grundlagen der K\u00fcnstlichen Intelligenz (KI), insbesondere mit Techniken des Schliessens unter Unsicherheit, des maschinellen Lernens und dem Sprachverstehen."}, {"title": "#9 - KI in der Versicherungsbranche", "itunes_title": null, "episode": "9", "date": "Tue, 12 Mar 2019 12:50:01 +0100", "link": "https://ga14i6.podcaster.de/aidriven/media/Podcast_9.mp3", "author": "Tobias Oberrauch & Willi Boogen", "description": "Wir sprechen \u00fcber KI in der Versicherungsbranche und die Zukunft von Expertenwissen in Zeiten der Digitalisierung", "summary": "Wir sprechen \u00fcber KI in der Versicherungsbranche und die Zukunft von Expertenwissen in Zeiten der Digitalisierung"}, {"title": "#5 - IT-Tech-Trends", "itunes_title": null, "episode": "5", "date": "Sat, 09 Mar 2019 10:26:46 +0100", "link": "https://ga14i6.podcaster.de/aidriven/media/Podcast_5.mp3", "author": "Tobias Oberrauch & Willi Boogen", "description": "WIPO-Studie: Patentwelle bei K\u00fcnstlicher Intelligenz rollt heran und&nbsp;Deloitte nennt 6 IT-Tech-Trends f\u00fcr 2019.<div>Links:&nbsp;<a href=\"https://www.heise.de/newsticker/meldung/WIPO-Studie-Patentwelle-bei-Kuenstlicher-Intelligenz-rollt-heran-4296540.html\">https://www.heise.de/newsticker/meldung/WIPO-Studie-Patentwelle-bei-Kuenstlicher-Intelligenz-rollt-heran-4296540.html</a>&nbsp;und&nbsp;<a href=\"https://www.cio.de/a/deloitte-nennt-6-it-tech-trends-fuer-2019,3594649\">https://www.cio.de/a/deloitte-nennt-6-it-tech-trends-fuer-2019,3594649</a></div>", "summary": "WIPO-Studie: Patentwelle bei K\u00fcnstlicher Intelligenz rollt heran und&nbsp;Deloitte nennt 6 IT-Tech-Trends f\u00fcr 2019.Links:&nbsp;https://www.heise.de/newsticker/meldung/WIPO-Studie-Patentwelle-bei-Kuenstlicher-Intelligenz-rollt-heran-4296540.html&nbsp;und&nbsp;https://www.cio.de/a/deloitte-nennt-6-it-tech-trends-fuer-2019,3594649"}, {"title": "#6 - Autonomes Fahren", "itunes_title": null, "episode": "6", "date": "Sat, 09 Mar 2019 10:25:39 +0100", "link": "https://ga14i6.podcaster.de/aidriven/media/Podcast_6(1).mp3", "author": "Tobias Oberrauch & Willi Boogen", "description": "Autonomes&nbsp;Fahren: Wir sprechen \u00fcber lukrative Business-Cases. Erster Master-Studiengang \u201eAutonomes Fahren\u201c startet und Nuro.ai erh\u00e4lt Finanzspritze \u00fcber 900 Millionen Dollar.&nbsp;<div>https://www.stuttgarter-zeitung.de/inhalt.in-baden-wuerttemberg-erster-master-studiengang-autonomes-fahren-startet.b34e537c-a53b-4ff8-8ee0-950f651c0926.html und https://www.heise.de/newsticker/meldung/Roboterauto-Nuro-ai-erhaelt-Finanzspritze-ueber-900-Millionen-Dollar-4305183.html?hg=1&amp;hgi=1&amp;hgf=false</div>", "summary": "Autonomes&nbsp;Fahren: Wir sprechen \u00fcber lukrative Business-Cases. Erster Master-Studiengang \u201eAutonomes Fahren\u201c startet und Nuro.ai erh\u00e4lt Finanzspritze \u00fcber 900 Millionen Dollar.&nbsp;https://www.stuttgarter-zeitung.de/inhalt.in-baden-wuerttemberg-erster-master-studiengang-autonomes-fahren-startet.b34e537c-a53b-4ff8-8ee0-950f651c0926.html und https://www.heise.de/newsticker/meldung/Roboterauto-Nuro-ai-erhaelt-Finanzspritze-ueber-900-Millionen-Dollar-4305183.html?hg=1&hgi=1&hgf=false"}, {"title": "#7 - KI in Europa", "itunes_title": null, "episode": "7", "date": "Sat, 09 Mar 2019 10:25:06 +0100", "link": "https://ga14i6.podcaster.de/aidriven/media/Podcast_7.mp3", "author": "Tobias Oberrauch & Willi Boogen", "description": "KI in Europa: Europa ist abgemeldet, EU f\u00f6rdert KI-Plattform, Claire AI und&nbsp;KI-Markt wird sich bis 2022 verf\u00fcnffachen", "summary": "KI in Europa: Europa ist abgemeldet, EU f\u00f6rdert KI-Plattform, Claire AI und&nbsp;KI-Markt wird sich bis 2022 verf\u00fcnffachen"}, {"title": "#8 - KI im Mittelstand", "itunes_title": null, "episode": "8", "date": "Sat, 09 Mar 2019 10:24:53 +0100", "link": "https://ga14i6.podcaster.de/aidriven/media/Podcast_8.mp3", "author": "Tobias Oberrauch & Willi Boogen", "description": "<div>Nur 17 % der Mittlelst\u00e4ndler setzen k\u00fcnstliche intelligenz ein!</div><div>Wir wollen das \u00e4ndern und geben euch 5 konkrete Schritte an die Hand, wie ihr k\u00fcnstliche intelligenz einsetzen k\u00f6nnt.</div><div><br></div>", "summary": "Nur 17 % der Mittlelst\u00e4ndler setzen k\u00fcnstliche intelligenz ein!Wir wollen das \u00e4ndern und geben euch 5 konkrete Schritte an die Hand, wie ihr k\u00fcnstliche intelligenz einsetzen k\u00f6nnt."}, {"title": "Podcast #4", "itunes_title": null, "episode": "4", "date": "Sat, 02 Feb 2019 12:20:48 +0100", "link": "https://ga14i6.podcaster.de/aidriven/media/Podcast_4.mp3", "author": "Tobias Oberrauch & Willi Boogen", "description": "Bosch will 25.000 Software-Experten einstellen und&nbsp;Data Scientists: Die gefragten Schatzsucher in Big Data.<div><a href=\"http://www.manager-magazin.de/unternehmen/autoindustrie/bosch-will-25-000-software-experten-einstellen-a-1250730.html\">http://www.manager-magazin.de/unternehmen/autoindustrie/bosch-will-25-000-software-experten-einstellen-a-1250730.html</a><br></div><div><a href=\"https://www.heise.de/newsticker/meldung/Data-Scientists-Die-gefragten-Schatzsucher-in-Big-Data-4292402.html\">https://www.heise.de/newsticker/meldung/Data-Scientists-Die-gefragten-Schatzsucher-in-Big-Data-4292402.html</a><br></div>", "summary": "Bosch will 25.000 Software-Experten einstellen und&nbsp;Data Scientists: Die gefragten Schatzsucher in Big Data.http://www.manager-magazin.de/unternehmen/autoindustrie/bosch-will-25-000-software-experten-einstellen-a-1250730.htmlhttps://www.heise.de/newsticker/meldung/Data-Scientists-Die-gefragten-Schatzsucher-in-Big-Data-4292402.html"}, {"title": "Podcast #3", "itunes_title": null, "episode": "3", "date": "Thu, 24 Jan 2019 20:55:10 +0100", "link": "https://ga14i6.podcaster.de/aidriven/media/Podcast_3.mp3", "author": "Tobias Oberrauch", "description": "<div>In dieser Folge reden wir dar\u00fcber warum IBM Watson in Deutschland im medizinschen Umfeld gescheitert ist, wieviel Unternehmen weltweit k\u00fcnstliche Intelligenz nutzen und geben dir einen Einblick dar\u00fcber, was aus aidrven mit deiner Hilfe werden kann.</div><div>Viel Spa\u00df damit!</div><div><br></div><div><a href=\"https://www.heise.de/tr/artikel/Dr-Watson-weiss-nicht-weiter-4282986.html\">https://www.heise.de/tr/artikel/Dr-Watson-weiss-nicht-weiter-4282986.html</a><br></div><div><a href=\"https://t3n.de/news/gartner-studie-37-prozent-nutzen-ki-1139201/\">https://t3n.de/news/gartner-studie-37-prozent-nutzen-ki-1139201/</a><br></div>", "summary": "In dieser Folge reden wir dar\u00fcber warum IBM Watson in Deutschland im medizinschen Umfeld gescheitert ist, wieviel Unternehmen weltweit k\u00fcnstliche Intelligenz nutzen und geben dir einen Einblick dar\u00fcber, was aus aidrven mit deiner Hilfe werden kann.Viel Spa\u00df damit!https://www.heise.de/tr/artikel/Dr-Watson-weiss-nicht-weiter-4282986.htmlhttps://t3n.de/news/gartner-studie-37-prozent-nutzen-ki-1139201/"}, {"title": "Podcast #2", "itunes_title": null, "episode": "2", "date": "Fri, 18 Jan 2019 18:31:22 +0100", "link": "https://ga14i6.podcaster.de/aidriven/media/Aufnahme(1).mp3", "author": "Tobias Oberrauch", "description": "<div>In dieser Folge sprechen wir \u00fcber das maschinelle Lernen bei Audi, von einer KI, die Parf\u00fcm kreiert und die Rolle des Menschen in der digitalen Welt.</div><div>Viele Spa\u00df damit :)</div><div>Euer Willi, euer Tobias</div><div><br></div><div><div><a href=\"https://www.cio.de/a/audi-nutzt-machine-learning-in-der-serienproduktion,3591147\">https://www.cio.de/a/audi-nutzt-machine-learning-in-der-serienproduktion,3591147</a><br></div><div><a href=\"https://www.zdf.de/nachrichten/heute/kuenstliche-intelligenz-entwickelt-parfum-100.html\">https://www.zdf.de/nachrichten/heute/kuenstliche-intelligenz-entwickelt-parfum-100.html</a><br></div></div>", "summary": "In dieser Folge sprechen wir \u00fcber das maschinelle Lernen bei Audi, von einer KI, die Parf\u00fcm kreiert und die Rolle des Menschen in der digitalen Welt.Viele Spa\u00df damit :)Euer Willi, euer Tobiashttps://www.cio.de/a/audi-nutzt-machine-learning-in-der-serienproduktion,3591147https://www.zdf.de/nachrichten/heute/kuenstliche-intelligenz-entwickelt-parfum-100.html"}, {"title": "Podcast #1", "itunes_title": null, "episode": "1", "date": "Fri, 11 Jan 2019 14:23:59 +0100", "link": "https://ga14i6.podcaster.de/aidriven/media/Aufnahme.mp3", "author": "Tobias Oberrauch", "description": "<p class=\"MsoNormal\">In dieser Folge sprechen wir \u00fcber das Interview mit Wolfgang Wahlster im Manager-Magazin. Dort spricht der Leiter vom DFKI \u00fcber die deutsche Schw\u00e4chen, chinesisches Marketingget\u00f6se und warum Deutschland seiner Ansicht in der KI besser dasteht, als viele glauben.</p>", "summary": "Der Podcast aidriven.business hilft bei der Einf\u00fchrung von k\u00fcnstlicher Intelligenz und schl\u00e4gt die Br\u00fccke zwischen der IT- und der Business-Welt.\n\nDie Initiatoren von aidriven stellen euch Tipps, Tools und Wissen bereit, damit diese Herkules-Aufgabe gelingen kann."}, {"title": "1 - K\u00fcnstliche Intelligenz II 2017", "itunes_title": null, "episode": null, "date": "Thu, 04 May 2017 00:00:00 +0200", "link": null, "author": "Prof. Dr. Michael Kohlhase", "description": null, "summary": "Dieser Kurs besch\u00e4ftigt sich mit den Grundlagen der K\u00fcnstlichen Intelligenz (KI), insbesondere mit Techniken des Schliessens unter Unsicherheit, des maschinellen Lernens und dem Sprachverstehen."}, {"title": "2 - K\u00fcnstliche Intelligenz II 2017", "itunes_title": null, "episode": null, "date": "Mon, 08 May 2017 00:00:00 +0200", "link": null, "author": "Prof. Dr. Michael Kohlhase", "description": null, "summary": "Dieser Kurs besch\u00e4ftigt sich mit den Grundlagen der K\u00fcnstlichen Intelligenz (KI), insbesondere mit Techniken des Schliessens unter Unsicherheit, des maschinellen Lernens und dem Sprachverstehen."}, {"title": "3 - K\u00fcnstliche Intelligenz II 2017", "itunes_title": null, "episode": null, "date": "Thu, 11 May 2017 00:00:00 +0200", "link": null, "author": "Prof. Dr. Michael Kohlhase", "description": null, "summary": "Dieser Kurs besch\u00e4ftigt sich mit den Grundlagen der K\u00fcnstlichen Intelligenz (KI), insbesondere mit Techniken des Schliessens unter Unsicherheit, des maschinellen Lernens und dem Sprachverstehen."}, {"title": "4 - K\u00fcnstliche Intelligenz II 2017", "itunes_title": null, "episode": null, "date": "Mon, 15 May 2017 00:00:00 +0200", "link": null, "author": "Prof. Dr. Michael Kohlhase", "description": null, "summary": "Dieser Kurs besch\u00e4ftigt sich mit den Grundlagen der K\u00fcnstlichen Intelligenz (KI), insbesondere mit Techniken des Schliessens unter Unsicherheit, des maschinellen Lernens und dem Sprachverstehen."}, {"title": "5 - K\u00fcnstliche Intelligenz II 2017", "itunes_title": null, "episode": null, "date": "Thu, 18 May 2017 00:00:00 +0200", "link": null, "author": "Prof. Dr. Michael Kohlhase", "description": null, "summary": "Dieser Kurs besch\u00e4ftigt sich mit den Grundlagen der K\u00fcnstlichen Intelligenz (KI), insbesondere mit Techniken des Schliessens unter Unsicherheit, des maschinellen Lernens und dem Sprachverstehen."}, {"title": "6 - K\u00fcnstliche Intelligenz II 2017", "itunes_title": null, "episode": null, "date": "Mon, 22 May 2017 00:00:00 +0200", "link": null, "author": "Prof. Dr. Michael Kohlhase", "description": null, "summary": "Dieser Kurs besch\u00e4ftigt sich mit den Grundlagen der K\u00fcnstlichen Intelligenz (KI), insbesondere mit Techniken des Schliessens unter Unsicherheit, des maschinellen Lernens und dem Sprachverstehen."}, {"title": "7 - K\u00fcnstliche Intelligenz II 2017", "itunes_title": null, "episode": null, "date": "Mon, 29 May 2017 00:00:00 +0200", "link": null, "author": "Prof. Dr. Michael Kohlhase", "description": null, "summary": "Dieser Kurs besch\u00e4ftigt sich mit den Grundlagen der K\u00fcnstlichen Intelligenz (KI), insbesondere mit Techniken des Schliessens unter Unsicherheit, des maschinellen Lernens und dem Sprachverstehen."}, {"title": "8 - K\u00fcnstliche Intelligenz II 2017", "itunes_title": null, "episode": null, "date": "Thu, 01 Jun 2017 00:00:00 +0200", "link": null, "author": "Prof. Dr. Michael Kohlhase", "description": null, "summary": "Dieser Kurs besch\u00e4ftigt sich mit den Grundlagen der K\u00fcnstlichen Intelligenz (KI), insbesondere mit Techniken des Schliessens unter Unsicherheit, des maschinellen Lernens und dem Sprachverstehen."}, {"title": "9 - K\u00fcnstliche Intelligenz II 2017", "itunes_title": null, "episode": null, "date": "Thu, 08 Jun 2017 00:00:00 +0200", "link": null, "author": "Prof. Dr. Michael Kohlhase", "description": null, "summary": "Dieser Kurs besch\u00e4ftigt sich mit den Grundlagen der K\u00fcnstlichen Intelligenz (KI), insbesondere mit Techniken des Schliessens unter Unsicherheit, des maschinellen Lernens und dem Sprachverstehen."}, {"title": "10 - K\u00fcnstliche Intelligenz II 2017", "itunes_title": null, "episode": null, "date": "Mon, 12 Jun 2017 00:00:00 +0200", "link": null, "author": "Prof. Dr. Michael Kohlhase", "description": null, "summary": "Dieser Kurs besch\u00e4ftigt sich mit den Grundlagen der K\u00fcnstlichen Intelligenz (KI), insbesondere mit Techniken des Schliessens unter Unsicherheit, des maschinellen Lernens und dem Sprachverstehen."}, {"title": "11 - K\u00fcnstliche Intelligenz II 2017", "itunes_title": null, "episode": null, "date": "Mon, 19 Jun 2017 00:00:00 +0200", "link": null, "author": "Prof. Dr. Michael Kohlhase", "description": null, "summary": "Dieser Kurs besch\u00e4ftigt sich mit den Grundlagen der K\u00fcnstlichen Intelligenz (KI), insbesondere mit Techniken des Schliessens unter Unsicherheit, des maschinellen Lernens und dem Sprachverstehen."}, {"title": "12 - K\u00fcnstliche Intelligenz II 2017", "itunes_title": null, "episode": null, "date": "Thu, 22 Jun 2017 00:00:00 +0200", "link": null, "author": "Prof. Dr. Michael Kohlhase", "description": null, "summary": "Dieser Kurs besch\u00e4ftigt sich mit den Grundlagen der K\u00fcnstlichen Intelligenz (KI), insbesondere mit Techniken des Schliessens unter Unsicherheit, des maschinellen Lernens und dem Sprachverstehen."}, {"title": "13 - K\u00fcnstliche Intelligenz II 2017", "itunes_title": null, "episode": null, "date": "Mon, 26 Jun 2017 00:00:00 +0200", "link": null, "author": "Prof. Dr. Michael Kohlhase", "description": null, "summary": "Dieser Kurs besch\u00e4ftigt sich mit den Grundlagen der K\u00fcnstlichen Intelligenz (KI), insbesondere mit Techniken des Schliessens unter Unsicherheit, des maschinellen Lernens und dem Sprachverstehen."}, {"title": "14 - K\u00fcnstliche Intelligenz II 2017", "itunes_title": null, "episode": null, "date": "Thu, 29 Jun 2017 00:00:00 +0200", "link": null, "author": "Prof. Dr. Michael Kohlhase", "description": null, "summary": "Dieser Kurs besch\u00e4ftigt sich mit den Grundlagen der K\u00fcnstlichen Intelligenz (KI), insbesondere mit Techniken des Schliessens unter Unsicherheit, des maschinellen Lernens und dem Sprachverstehen."}, {"title": "15 - K\u00fcnstliche Intelligenz II 2017", "itunes_title": null, "episode": null, "date": "Mon, 03 Jul 2017 00:00:00 +0200", "link": null, "author": "Prof. Dr. Michael Kohlhase", "description": null, "summary": "Dieser Kurs besch\u00e4ftigt sich mit den Grundlagen der K\u00fcnstlichen Intelligenz (KI), insbesondere mit Techniken des Schliessens unter Unsicherheit, des maschinellen Lernens und dem Sprachverstehen."}, {"title": "16 - K\u00fcnstliche Intelligenz II 2017", "itunes_title": null, "episode": null, "date": "Thu, 06 Jul 2017 00:00:00 +0200", "link": null, "author": "Prof. Dr. Michael Kohlhase", "description": null, "summary": "Dieser Kurs besch\u00e4ftigt sich mit den Grundlagen der K\u00fcnstlichen Intelligenz (KI), insbesondere mit Techniken des Schliessens unter Unsicherheit, des maschinellen Lernens und dem Sprachverstehen."}, {"title": "17 - K\u00fcnstliche Intelligenz II 2017", "itunes_title": null, "episode": null, "date": "Mon, 10 Jul 2017 00:00:00 +0200", "link": null, "author": "Dennis M\u00fcller", "description": null, "summary": "Dieser Kurs besch\u00e4ftigt sich mit den Grundlagen der K\u00fcnstlichen Intelligenz (KI), insbesondere mit Techniken des Schliessens unter Unsicherheit, des maschinellen Lernens und dem Sprachverstehen."}, {"title": "18 - K\u00fcnstliche Intelligenz II 2017", "itunes_title": null, "episode": null, "date": "Thu, 13 Jul 2017 00:00:00 +0200", "link": null, "author": "Dennis M\u00fcller", "description": null, "summary": "Dieser Kurs besch\u00e4ftigt sich mit den Grundlagen der K\u00fcnstlichen Intelligenz (KI), insbesondere mit Techniken des Schliessens unter Unsicherheit, des maschinellen Lernens und dem Sprachverstehen."}, {"title": "19 - K\u00fcnstliche Intelligenz II 2017", "itunes_title": null, "episode": null, "date": "Mon, 17 Jul 2017 00:00:00 +0200", "link": null, "author": "Marcel Rupprecht", "description": null, "summary": "Dieser Kurs besch\u00e4ftigt sich mit den Grundlagen der K\u00fcnstlichen Intelligenz (KI), insbesondere mit Techniken des Schliessens unter Unsicherheit, des maschinellen Lernens und dem Sprachverstehen."}, {"title": "20 - K\u00fcnstliche Intelligenz II 2017", "itunes_title": null, "episode": null, "date": "Mon, 24 Jul 2017 00:00:00 +0200", "link": null, "author": "Prof. Dr. Michael Kohlhase", "description": null, "summary": "Dieser Kurs besch\u00e4ftigt sich mit den Grundlagen der K\u00fcnstlichen Intelligenz (KI), insbesondere mit Techniken des Schliessens unter Unsicherheit, des maschinellen Lernens und dem Sprachverstehen."}, {"title": "21 - K\u00fcnstliche Intelligenz II 2017", "itunes_title": null, "episode": null, "date": "Thu, 27 Jul 2017 00:00:00 +0200", "link": null, "author": "Prof. Dr. Michael Kohlhase", "description": null, "summary": "Dieser Kurs besch\u00e4ftigt sich mit den Grundlagen der K\u00fcnstlichen Intelligenz (KI), insbesondere mit Techniken des Schliessens unter Unsicherheit, des maschinellen Lernens und dem Sprachverstehen."}, {"title": "Roboter-Visionen - Von den Statuen des D\u00e4dalos zu Ava 2018", "itunes_title": null, "episode": null, "date": "Thu, 19 Apr 2018 00:00:00 +0200", "link": null, "author": "Dr. Bernd Flessner", "description": null, "summary": "Im Rahmen der Mensch-Roboter Kollaboration werden zuk\u00fcnftig Mensch und Roboter in der Produktion sowohl \u00f6rtlich als auch physisch zusammenarbeiten. Der Mensch \u00fcbernimmt bei dieser Kollaboration die anspruchsvolleren T\u00e4tigkeiten, insbesondere die \u00dcberwachung und die Steuerung des Produktionsablaufs. Der Roboter \u00fcbernimmt k\u00f6rperlich anstrengende, monotone oder anspruchslose Aufgaben. Dies erfordert intuitive und zuverl\u00e4ssige Schnittstellen und Kommunikationsformen zur Gestaltung der Mensch-Roboter Kommunikation."}, {"title": "Aktuelle Entwicklungen in der Robotik 2018", "itunes_title": null, "episode": null, "date": "Thu, 26 Apr 2018 00:00:00 +0200", "link": null, "author": "Prof. Dr. Ronald Schmidt-Vollus", "description": null, "summary": "Im Rahmen der Mensch-Roboter Kollaboration werden zuk\u00fcnftig Mensch und Roboter in der Produktion sowohl \u00f6rtlich als auch physisch zusammenarbeiten. Dies erfordert intuitive und zuverl\u00e4ssige Schnittstellen und Kommunikationsformen zur Gestaltung der Mensch-Roboter Kommunikation. Dieser Vortrag beschreibt zun\u00e4chst den Stand der Technik bzw. aktuelle Entwicklungen im Bereich der Robotik ganz allgemein und geht dann speziell auf aktuelle Forschungsaktivit\u00e4ten zur Gestaltung der Mensch-Roboter Kommunikation f\u00fcr kollaborierende Industrieroboter ein."}, {"title": "Herausforderungen f\u00fcr das Recht durch moderne technische Entwicklungen 2018", "itunes_title": null, "episode": null, "date": "Thu, 03 May 2018 00:00:00 +0200", "link": null, "author": "Prof. Dr. Franz Hofmann", "description": null, "summary": "Roboterrasenm\u00e4her, selbstfahrende Autos oder auch automatische Sucherg\u00e4nzungs\u00advorschl\u00e4ge bei Google: Wenn \u201eRoboter\u201c statt Menschen handeln, scheinen sich eine Vielzahl von Rechtsfragen neu zu stellen. Der Vortrag stellt juristische Haftungskonzepte vor, will aber vor allem f\u00fcr die Fragen sensibilisieren, die sich der Jurist neu zu stellen hat.\n\nBei dem im Video zu sehenden Roboter handelt es sich um \u201ePepper\u201c, vgl. https://www.softbankrobotics.com/emea/en/press/gallery/pepper. Vgl. zudem Gemeinschaftsgeschmacksmusters: 002224048-0001, https://register.dpma.de/DPMAregister/gsm/registerhabm?DNR=002224048-0001.\n\n\u00a0"}, {"title": "1 - K\u00fcnstliche Intelligenz II 2017", "itunes_title": null, "episode": null, "date": "Thu, 04 May 2017 00:00:00 +0200", "link": null, "author": "Prof. Dr. Michael Kohlhase", "description": null, "summary": "Dieser Kurs besch\u00e4ftigt sich mit den Grundlagen der K\u00fcnstlichen Intelligenz (KI), insbesondere mit Techniken des Schliessens unter Unsicherheit, des maschinellen Lernens und dem Sprachverstehen."}, {"title": "2 - K\u00fcnstliche Intelligenz II 2017", "itunes_title": null, "episode": null, "date": "Mon, 08 May 2017 00:00:00 +0200", "link": null, "author": "Prof. Dr. Michael Kohlhase", "description": null, "summary": "Dieser Kurs besch\u00e4ftigt sich mit den Grundlagen der K\u00fcnstlichen Intelligenz (KI), insbesondere mit Techniken des Schliessens unter Unsicherheit, des maschinellen Lernens und dem Sprachverstehen."}, {"title": "3 - K\u00fcnstliche Intelligenz II 2017", "itunes_title": null, "episode": null, "date": "Thu, 11 May 2017 00:00:00 +0200", "link": null, "author": "Prof. Dr. Michael Kohlhase", "description": null, "summary": "Dieser Kurs besch\u00e4ftigt sich mit den Grundlagen der K\u00fcnstlichen Intelligenz (KI), insbesondere mit Techniken des Schliessens unter Unsicherheit, des maschinellen Lernens und dem Sprachverstehen."}, {"title": "4 - K\u00fcnstliche Intelligenz II 2017", "itunes_title": null, "episode": null, "date": "Mon, 15 May 2017 00:00:00 +0200", "link": null, "author": "Prof. Dr. Michael Kohlhase", "description": null, "summary": "Dieser Kurs besch\u00e4ftigt sich mit den Grundlagen der K\u00fcnstlichen Intelligenz (KI), insbesondere mit Techniken des Schliessens unter Unsicherheit, des maschinellen Lernens und dem Sprachverstehen."}, {"title": "5 - K\u00fcnstliche Intelligenz II 2017", "itunes_title": null, "episode": null, "date": "Thu, 18 May 2017 00:00:00 +0200", "link": null, "author": "Prof. Dr. Michael Kohlhase", "description": null, "summary": "Dieser Kurs besch\u00e4ftigt sich mit den Grundlagen der K\u00fcnstlichen Intelligenz (KI), insbesondere mit Techniken des Schliessens unter Unsicherheit, des maschinellen Lernens und dem Sprachverstehen."}, {"title": "6 - K\u00fcnstliche Intelligenz II 2017", "itunes_title": null, "episode": null, "date": "Mon, 22 May 2017 00:00:00 +0200", "link": null, "author": "Prof. Dr. Michael Kohlhase", "description": null, "summary": "Dieser Kurs besch\u00e4ftigt sich mit den Grundlagen der K\u00fcnstlichen Intelligenz (KI), insbesondere mit Techniken des Schliessens unter Unsicherheit, des maschinellen Lernens und dem Sprachverstehen."}, {"title": "7 - K\u00fcnstliche Intelligenz II 2017", "itunes_title": null, "episode": null, "date": "Mon, 29 May 2017 00:00:00 +0200", "link": null, "author": "Prof. Dr. Michael Kohlhase", "description": null, "summary": "Dieser Kurs besch\u00e4ftigt sich mit den Grundlagen der K\u00fcnstlichen Intelligenz (KI), insbesondere mit Techniken des Schliessens unter Unsicherheit, des maschinellen Lernens und dem Sprachverstehen."}, {"title": "8 - K\u00fcnstliche Intelligenz II 2017", "itunes_title": null, "episode": null, "date": "Thu, 01 Jun 2017 00:00:00 +0200", "link": null, "author": "Prof. Dr. Michael Kohlhase", "description": null, "summary": "Dieser Kurs besch\u00e4ftigt sich mit den Grundlagen der K\u00fcnstlichen Intelligenz (KI), insbesondere mit Techniken des Schliessens unter Unsicherheit, des maschinellen Lernens und dem Sprachverstehen."}, {"title": "9 - K\u00fcnstliche Intelligenz II 2017", "itunes_title": null, "episode": null, "date": "Thu, 08 Jun 2017 00:00:00 +0200", "link": null, "author": "Prof. Dr. Michael Kohlhase", "description": null, "summary": "Dieser Kurs besch\u00e4ftigt sich mit den Grundlagen der K\u00fcnstlichen Intelligenz (KI), insbesondere mit Techniken des Schliessens unter Unsicherheit, des maschinellen Lernens und dem Sprachverstehen."}, {"title": "10 - K\u00fcnstliche Intelligenz II 2017", "itunes_title": null, "episode": null, "date": "Mon, 12 Jun 2017 00:00:00 +0200", "link": null, "author": "Prof. Dr. Michael Kohlhase", "description": null, "summary": "Dieser Kurs besch\u00e4ftigt sich mit den Grundlagen der K\u00fcnstlichen Intelligenz (KI), insbesondere mit Techniken des Schliessens unter Unsicherheit, des maschinellen Lernens und dem Sprachverstehen."}, {"title": "11 - K\u00fcnstliche Intelligenz II 2017", "itunes_title": null, "episode": null, "date": "Mon, 19 Jun 2017 00:00:00 +0200", "link": null, "author": "Prof. Dr. Michael Kohlhase", "description": null, "summary": "Dieser Kurs besch\u00e4ftigt sich mit den Grundlagen der K\u00fcnstlichen Intelligenz (KI), insbesondere mit Techniken des Schliessens unter Unsicherheit, des maschinellen Lernens und dem Sprachverstehen."}, {"title": "12 - K\u00fcnstliche Intelligenz II 2017", "itunes_title": null, "episode": null, "date": "Thu, 22 Jun 2017 00:00:00 +0200", "link": null, "author": "Prof. Dr. Michael Kohlhase", "description": null, "summary": "Dieser Kurs besch\u00e4ftigt sich mit den Grundlagen der K\u00fcnstlichen Intelligenz (KI), insbesondere mit Techniken des Schliessens unter Unsicherheit, des maschinellen Lernens und dem Sprachverstehen."}, {"title": "13 - K\u00fcnstliche Intelligenz II 2017", "itunes_title": null, "episode": null, "date": "Mon, 26 Jun 2017 00:00:00 +0200", "link": null, "author": "Prof. Dr. Michael Kohlhase", "description": null, "summary": "Dieser Kurs besch\u00e4ftigt sich mit den Grundlagen der K\u00fcnstlichen Intelligenz (KI), insbesondere mit Techniken des Schliessens unter Unsicherheit, des maschinellen Lernens und dem Sprachverstehen."}, {"title": "14 - K\u00fcnstliche Intelligenz II 2017", "itunes_title": null, "episode": null, "date": "Thu, 29 Jun 2017 00:00:00 +0200", "link": null, "author": "Prof. Dr. Michael Kohlhase", "description": null, "summary": "Dieser Kurs besch\u00e4ftigt sich mit den Grundlagen der K\u00fcnstlichen Intelligenz (KI), insbesondere mit Techniken des Schliessens unter Unsicherheit, des maschinellen Lernens und dem Sprachverstehen."}, {"title": "15 - K\u00fcnstliche Intelligenz II 2017", "itunes_title": null, "episode": null, "date": "Mon, 03 Jul 2017 00:00:00 +0200", "link": null, "author": "Prof. Dr. Michael Kohlhase", "description": null, "summary": "Dieser Kurs besch\u00e4ftigt sich mit den Grundlagen der K\u00fcnstlichen Intelligenz (KI), insbesondere mit Techniken des Schliessens unter Unsicherheit, des maschinellen Lernens und dem Sprachverstehen."}, {"title": "16 - K\u00fcnstliche Intelligenz II 2017", "itunes_title": null, "episode": null, "date": "Thu, 06 Jul 2017 00:00:00 +0200", "link": null, "author": "Prof. Dr. Michael Kohlhase", "description": null, "summary": "Dieser Kurs besch\u00e4ftigt sich mit den Grundlagen der K\u00fcnstlichen Intelligenz (KI), insbesondere mit Techniken des Schliessens unter Unsicherheit, des maschinellen Lernens und dem Sprachverstehen."}, {"title": "17 - K\u00fcnstliche Intelligenz II 2017", "itunes_title": null, "episode": null, "date": "Mon, 10 Jul 2017 00:00:00 +0200", "link": null, "author": "Dennis M\u00fcller", "description": null, "summary": "Dieser Kurs besch\u00e4ftigt sich mit den Grundlagen der K\u00fcnstlichen Intelligenz (KI), insbesondere mit Techniken des Schliessens unter Unsicherheit, des maschinellen Lernens und dem Sprachverstehen."}, {"title": "18 - K\u00fcnstliche Intelligenz II 2017", "itunes_title": null, "episode": null, "date": "Thu, 13 Jul 2017 00:00:00 +0200", "link": null, "author": "Dennis M\u00fcller", "description": null, "summary": "Dieser Kurs besch\u00e4ftigt sich mit den Grundlagen der K\u00fcnstlichen Intelligenz (KI), insbesondere mit Techniken des Schliessens unter Unsicherheit, des maschinellen Lernens und dem Sprachverstehen."}, {"title": "19 - K\u00fcnstliche Intelligenz II 2017", "itunes_title": null, "episode": null, "date": "Mon, 17 Jul 2017 00:00:00 +0200", "link": null, "author": "Marcel Rupprecht", "description": null, "summary": "Dieser Kurs besch\u00e4ftigt sich mit den Grundlagen der K\u00fcnstlichen Intelligenz (KI), insbesondere mit Techniken des Schliessens unter Unsicherheit, des maschinellen Lernens und dem Sprachverstehen."}, {"title": "20 - K\u00fcnstliche Intelligenz II 2017", "itunes_title": null, "episode": null, "date": "Mon, 24 Jul 2017 00:00:00 +0200", "link": null, "author": "Prof. Dr. Michael Kohlhase", "description": null, "summary": "Dieser Kurs besch\u00e4ftigt sich mit den Grundlagen der K\u00fcnstlichen Intelligenz (KI), insbesondere mit Techniken des Schliessens unter Unsicherheit, des maschinellen Lernens und dem Sprachverstehen."}, {"title": "21 - K\u00fcnstliche Intelligenz II 2017", "itunes_title": null, "episode": null, "date": "Thu, 27 Jul 2017 00:00:00 +0200", "link": null, "author": "Prof. Dr. Michael Kohlhase", "description": null, "summary": "Dieser Kurs besch\u00e4ftigt sich mit den Grundlagen der K\u00fcnstlichen Intelligenz (KI), insbesondere mit Techniken des Schliessens unter Unsicherheit, des maschinellen Lernens und dem Sprachverstehen."}, {"title": "Roboter-Visionen - Von den Statuen des D\u00e4dalos zu Ava 2018", "itunes_title": null, "episode": null, "date": "Thu, 19 Apr 2018 00:00:00 +0200", "link": null, "author": "Dr. Bernd Flessner", "description": null, "summary": "Im Rahmen der Mensch-Roboter Kollaboration werden zuk\u00fcnftig Mensch und Roboter in der Produktion sowohl \u00f6rtlich als auch physisch zusammenarbeiten. Der Mensch \u00fcbernimmt bei dieser Kollaboration die anspruchsvolleren T\u00e4tigkeiten, insbesondere die \u00dcberwachung und die Steuerung des Produktionsablaufs. Der Roboter \u00fcbernimmt k\u00f6rperlich anstrengende, monotone oder anspruchslose Aufgaben. Dies erfordert intuitive und zuverl\u00e4ssige Schnittstellen und Kommunikationsformen zur Gestaltung der Mensch-Roboter Kommunikation."}, {"title": "1 - Mathematische Grundlagen zu Data Analytics, Neuronale Netze und K\u00fcnstliche Intelligenz 2019", "itunes_title": null, "episode": null, "date": "Mon, 15 Apr 2019 00:00:00 +0200", "link": null, "author": "Dr. Hans Georg Zimmermann", "description": null, "summary": ""}, {"title": "2 - Mathematische Grundlagen zu Data Analytics, Neuronale Netze und K\u00fcnstliche Intelligenz 2019", "itunes_title": null, "episode": null, "date": "Mon, 15 Apr 2019 00:00:00 +0200", "link": null, "author": "Dr. Hans Georg Zimmermann", "description": null, "summary": ""}, {"title": "3 - Mathematische Grundlagen zu Data Analytics, Neuronale Netze und K\u00fcnstliche Intelligenz 2019", "itunes_title": null, "episode": null, "date": "Mon, 15 Apr 2019 00:00:00 +0200", "link": null, "author": "Dr. Hans Georg Zimmermann", "description": null, "summary": ""}, {"title": "4 - Mathematische Grundlagen zu Data Analytics, Neuronale Netze und K\u00fcnstliche Intelligenz 2019", "itunes_title": null, "episode": null, "date": "Mon, 15 Apr 2019 00:00:00 +0200", "link": null, "author": "Dr. Hans Georg Zimmermann", "description": null, "summary": ""}, {"title": "7 - Mathematische Grundlagen zu Data Analytics, Neuronale Netze und K\u00fcnstliche Intelligenz 2019", "itunes_title": null, "episode": null, "date": "Tue, 16 Apr 2019 00:00:00 +0200", "link": null, "author": "Dr. Hans Georg Zimmermann", "description": null, "summary": ""}, {"title": "8 - Mathematische Grundlagen zu Data Analytics, Neuronale Netze und K\u00fcnstliche Intelligenz 2019", "itunes_title": null, "episode": null, "date": "Tue, 16 Apr 2019 00:00:00 +0200", "link": null, "author": "Dr. Hans Georg Zimmermann", "description": null, "summary": ""}, {"title": "9 - Mathematische Grundlagen zu Data Analytics, Neuronale Netze und K\u00fcnstliche Intelligenz 2019", "itunes_title": null, "episode": null, "date": "Wed, 17 Apr 2019 00:00:00 +0200", "link": null, "author": "Dr. Hans Georg Zimmermann", "description": null, "summary": ""}, {"title": "10 - Mathematische Grundlagen zu Data Analytics, Neuronale Netze und K\u00fcnstliche Intelligenz 2019", "itunes_title": null, "episode": null, "date": "Wed, 17 Apr 2019 00:00:00 +0200", "link": null, "author": "Dr. Hans Georg Zimmermann", "description": null, "summary": ""}, {"title": "11 - Mathematische Grundlagen zu Data Analytics, Neuronale Netze und K\u00fcnstliche Intelligenz 2019", "itunes_title": null, "episode": null, "date": "Wed, 17 Apr 2019 00:00:00 +0200", "link": null, "author": "Dr. Hans Georg Zimmermann", "description": null, "summary": ""}, {"title": "12 - Mathematische Grundlagen zu Data Analytics, Neuronale Netze und K\u00fcnstliche Intelligenz 2019", "itunes_title": null, "episode": null, "date": "Wed, 17 Apr 2019 00:00:00 +0200", "link": null, "author": "Dr. Hans Georg Zimmermann", "description": null, "summary": ""}, {"title": "13 - Mathematische Grundlagen zu Data Analytics, Neuronale Netze und K\u00fcnstliche Intelligenz 2019", "itunes_title": null, "episode": null, "date": "Thu, 18 Apr 2019 00:00:00 +0200", "link": null, "author": "Dr. Hans Georg Zimmermann", "description": null, "summary": ""}, {"title": "14 - Mathematische Grundlagen zu Data Analytics, Neuronale Netze und K\u00fcnstliche Intelligenz 2019", "itunes_title": null, "episode": null, "date": "Thu, 18 Apr 2019 00:00:00 +0200", "link": null, "author": "Dr. Hans Georg Zimmermann", "description": null, "summary": ""}, {"title": "15 - Mathematische Grundlagen zu Data Analytics, Neuronale Netze und K\u00fcnstliche Intelligenz 2019", "itunes_title": null, "episode": null, "date": "Thu, 18 Apr 2019 00:00:00 +0200", "link": null, "author": "Dr. Hans Georg Zimmermann", "description": null, "summary": ""}, {"title": "16 - Mathematische Grundlagen zu Data Analytics, Neuronale Netze und K\u00fcnstliche Intelligenz 2019", "itunes_title": null, "episode": null, "date": "Thu, 18 Apr 2019 00:00:00 +0200", "link": null, "author": "Dr. Hans Georg Zimmermann", "description": null, "summary": ""}]